calc_taeg/__init__.py
calc_taeg/test_taeg.py
calc_taeg-1.0.2.dist-info/LICENSE
calc_taeg-1.0.2.dist-info/METADATA
calc_taeg-1.0.2.dist-info/WHEEL
calc_taeg-1.0.2.dist-info/top_level.txt
calc_taeg-1.0.2.dist-info/RECORD
