Metadata-Version: 2.1
Name: calc-taeg
Version: 1.0.2
Summary: Calcul du taux annuel effectif global
Author-email: Thibaut_S <py@outils-jcp.fr>
License: MIT-License
Project-URL: Homepage, https://gitlab.com/outils-jcp/calc-taeg
Project-URL: Bug Tracker, https://gitlab.com/outils-jcp/calc-taeg/-/issues
Keywords: taux,taeg,credit
Classifier: Programming Language :: Python :: 3
Requires-Python: >=3.8
License-File: LICENSE
Requires-Dist: fr-date
Provides-Extra: dev
Requires-Dist: wheel ; extra == 'dev'
Requires-Dist: pytest ; extra == 'dev'
Requires-Dist: ruff ; extra == 'dev'
Requires-Dist: black ; extra == 'dev'
Requires-Dist: pip-tools ; extra == 'dev'
Requires-Dist: twine ; extra == 'dev'
